opentrons_http_api/api.py
opentrons_http_api/defs/dict_data.py
opentrons_http_api/defs/enums.py
opentrons_http_api/defs/paths.py
opentrons_http_api/robot_client.py
opentrons_http_api/utils/parameterize_protocol.py
opentrons_http_api-1.5.0.dist-info/LICENSE
opentrons_http_api-1.5.0.dist-info/METADATA
opentrons_http_api-1.5.0.dist-info/WHEEL
opentrons_http_api-1.5.0.dist-info/RECORD
