Metadata-Version: 2.3
Name: opentrons-http-api
Version: 1.5.0
Summary: Python client for the Opentrons HTTP API (https://github.com/Opentrons/opentrons-integration-tools/tree/main/http-api)
Author: morefigs
Requires-Python: >=3.9,<4.0
Classifier: Programming Language :: Python :: 3
Classifier: Programming Language :: Python :: 3.9
Classifier: Programming Language :: Python :: 3.10
Classifier: Programming Language :: Python :: 3.11
Classifier: Programming Language :: Python :: 3.12
Classifier: Programming Language :: Python :: 3.13
Requires-Dist: requests (>=2.31.0,<3.0.0)
Project-URL: Homepage, https://github.com/morefigs/opentrons-http-api
